wordx/__init__.py
wordx/document.py
wordx/mixins.py
wordx/sheet.py
wordx/word_file.py
wordx/utils/fake_zip.py
wordx/utils/tree.py
wordx-0.4.8.dist-info/METADATA
wordx-0.4.8.dist-info/WHEEL
wordx-0.4.8.dist-info/licenses/LICENSE
wordx-0.4.8.dist-info/RECORD
