Metadata-Version: 2.1
Name: wordx
Version: 0.4.8
Summary: generate word documents in a sexy way
Project-URL: Homepage, https://github.com/inspirare6/wordx
Project-URL: Bug Tracker, https://github.com/inspirare6/wordx/issues
Author-email: inspirare6 <inspirare6@163.com>
License-File: LICENSE
Classifier: License :: OSI Approved :: MIT License
Classifier: Operating System :: OS Independent
Classifier: Programming Language :: Python :: 3
Requires-Python: >=3.7
Requires-Dist: jinja2==3.1.2
Requires-Dist: lxml==4.9.2
